[
  {
    "full_name": "backstage/backstage",
    "stargazers_count": 12253,
    "open_issues_count": 308,
    "forks_count": 1336
  },
  {
    "full_name": "gatsbyjs/gatsby",
    "stargazers_count": 50666,
    "open_issues_count": 443,
    "forks_count": 9683
  },
  {
    "full_name": "ant-design/ant-design",
    "stargazers_count": 72810,
    "open_issues_count": 671,
    "forks_count": 28807
  },
  {
    "full_name": "uber/baseweb",
    "stargazers_count": 6507,
    "open_issues_count": 103,
    "forks_count": 587
  },
  {
    "full_name": "Kong/insomnia",
    "stargazers_count": 16700,
    "open_issues_count": 499,
    "forks_count": 1052
  },
  {
    "full_name": "mui-org/material-ui",
    "stargazers_count": 69088,
    "open_issues_count": 514,
    "forks_count": 22682
  }
]